{"ugi.net.in.idealgroups.org":{"accounts":{},"account_count":0},"digicard.idealgroups.org":{"account_count":0,"accounts":{}},"web.idealgroups.org":{"account_count":0,"accounts":{}},"fizznfreeze.idealgroups.org":{"account_count":0,"accounts":{}},"idealgroups.org":{"quota_mtime":1784710344,"disk_mtime":1784710344,"account_count":6,"accounts":{"hr":{"diskmtime":1784710344,"diskused":"54448","suspended_login":0,"diskquota":"262144000"},"support":{"diskquota":"262144000","suspended_login":0,"diskmtime":1784710344,"diskused":"54548"},"rizvan":{"suspended_login":0,"diskquota":"262144000","diskmtime":1784710344,"diskused":"55007"},"rizvanshekh":{"diskmtime":1784710344,"diskused":"1133623","diskquota":"262144000","suspended_login":0},"hr_head":{"diskused":"1675642","diskmtime":1784710344,"diskquota":"262144000","suspended_login":0},"darshan.jain":{"diskused":"54337","diskmtime":1784710344,"diskquota":"262144000","suspended_login":0}},"shadow_mtime":1784710344},"ugi.idealgroups.org":{"accounts":{},"account_count":0},"__version":3,"kmanimalhealthcare.idealgroups.org":{"accounts":{},"account_count":0},"ugi.net.in":{"accounts":{},"account_count":0}}